mqtt2influxdb/__init__.py
mqtt2influxdb/cli.py
mqtt2influxdb/config.py
mqtt2influxdb/expr.py
mqtt2influxdb/mqtt2influxdb.py
mqtt2influxdb-2.0.6.dist-info/METADATA
mqtt2influxdb-2.0.6.dist-info/WHEEL
mqtt2influxdb-2.0.6.dist-info/entry_points.txt
mqtt2influxdb-2.0.6.dist-info/licenses/LICENSE
mqtt2influxdb-2.0.6.dist-info/RECORD
