Metadata-Version: 2.4
Name: mqtt2influxdb
Version: 2.0.6
Summary: MQTT to InfluxDB v3 bridge with flexible JSONPath transformation
Project-URL: Homepage, https://github.com/hardwario/mqtt2influxdb
Project-URL: Repository, https://github.com/hardwario/mqtt2influxdb
Author-email: "HARDWARIO a.s." <ask@hardwario.com>
License-Expression: MIT
License-File: LICENSE
Keywords: hardwario,influxdb,iot,mqtt,tower
Classifier: Development Status :: 5 - Production/Stable
Classifier: Environment :: Console
Classifier: License :: OSI Approved :: MIT License
Classifier: Operating System :: OS Independent
Classifier: Programming Language :: Python :: 3
Classifier: Programming Language :: Python :: 3.10
Classifier: Programming Language :: Python :: 3.11
Classifier: Programming Language :: Python :: 3.12
Classifier: Programming Language :: Python :: 3.13
Classifier: Topic :: Utilities
Requires-Python: >=3.10
Requires-Dist: click>=8.1
Requires-Dist: influxdb3-python>=0.10
Requires-Dist: jsonpath-ng>=1.6
Requires-Dist: paho-mqtt>=2.0
Requires-Dist: py-expression-eval>=0.3.14
Requires-Dist: pycron>=3.0
Requires-Dist: pydantic>=2.0
Requires-Dist: pyyaml>=6.0
Requires-Dist: requests>=2.31
